discotheque/__init__.py
discotheque-0.0.1.dist-info/LICENSE
discotheque-0.0.1.dist-info/WHEEL
discotheque-0.0.1.dist-info/METADATA
discotheque-0.0.1.dist-info/RECORD
