Metadata-Version: 2.1
Name: discotheque
Version: 0.0.1
Summary: Discotheque is a discovery system toolkit
Author-email: Daniel Opitz <daniel@dxio.de>
Classifier: License :: OSI Approved :: GNU General Public License v3 or later (GPLv3+)
Project-URL: Home, https://codeberg.org/od/discotheque
